id4me_rp_client/__init__.py
id4me_rp_client/id4me_constants.py
id4me_rp_client/id4me_exceptions.py
id4me_rp_client/id4me_rp_client.py
id4me_rp_client/network.py
id4me_rp_client/helper/__init__.py
id4me_rp_client/helper/stringify_keys.py
id4me_rp_client-0.0.24.dist-info/LICENSE
id4me_rp_client-0.0.24.dist-info/METADATA
id4me_rp_client-0.0.24.dist-info/WHEEL
id4me_rp_client-0.0.24.dist-info/top_level.txt
id4me_rp_client-0.0.24.dist-info/RECORD
