Metadata-Version: 2.1
Name: id4me-rp-client
Version: 0.0.24
Summary: Python client library for ID4me protocol - Relying Party side. See: https://id4me.org
Home-page: https://gitlab.com/ID4me/id4me-rp-client-python
Author: Pawel Kowalik
Author-email: pawel-kow@users.noreply.github.com
License: https://gitlab.com/ID4me/id4me-rp-client-python/blob/master/LICENSE
Platform: UNKNOWN
Classifier: Programming Language :: Python :: 2.7
Classifier: Programming Language :: Python :: 3.6
Classifier: Programming Language :: Python :: 3.7
Requires-Dist: dnspython (>=1.15.0)
Requires-Dist: six (>=1.11.0)
Requires-Dist: future (>=0.16.0)
Requires-Dist: jwcrypto (>=0.5.0)
